scikit_llm-1.4.3.dist-info/licenses/LICENSE
skllm/__init__.py
skllm/classification.py
skllm/config.py
skllm/model_constants.py
skllm/text2text.py
skllm/vectorization.py
skllm/datasets/__init__.py
skllm/datasets/multi_class.py
skllm/datasets/multi_label.py
skllm/datasets/summarization.py
skllm/datasets/translation.py
skllm/llm/base.py
skllm/llm/anthropic/completion.py
skllm/llm/anthropic/credentials.py
skllm/llm/anthropic/mixin.py
skllm/llm/gpt/completion.py
skllm/llm/gpt/embedding.py
skllm/llm/gpt/mixin.py
skllm/llm/gpt/utils.py
skllm/llm/gpt/clients/llama_cpp/completion.py
skllm/llm/gpt/clients/llama_cpp/handler.py
skllm/llm/gpt/clients/openai/completion.py
skllm/llm/gpt/clients/openai/credentials.py
skllm/llm/gpt/clients/openai/embedding.py
skllm/llm/gpt/clients/openai/tuning.py
skllm/llm/vertex/completion.py
skllm/llm/vertex/mixin.py
skllm/llm/vertex/tuning.py
skllm/memory/__init__.py
skllm/memory/_annoy.py
skllm/memory/_sklearn_nn.py
skllm/memory/base.py
skllm/models/_base/classifier.py
skllm/models/_base/tagger.py
skllm/models/_base/text2text.py
skllm/models/_base/vectorizer.py
skllm/models/anthropic/classification/few_shot.py
skllm/models/anthropic/classification/zero_shot.py
skllm/models/anthropic/tagging/ner.py
skllm/models/anthropic/text2text/__init__.py
skllm/models/anthropic/text2text/summarization.py
skllm/models/anthropic/text2text/translation.py
skllm/models/gpt/vectorization.py
skllm/models/gpt/classification/few_shot.py
skllm/models/gpt/classification/tunable.py
skllm/models/gpt/classification/zero_shot.py
skllm/models/gpt/tagging/ner.py
skllm/models/gpt/text2text/__init__.py
skllm/models/gpt/text2text/summarization.py
skllm/models/gpt/text2text/translation.py
skllm/models/gpt/text2text/tunable.py
skllm/models/vertex/classification/tunable.py
skllm/models/vertex/classification/zero_shot.py
skllm/models/vertex/text2text/__init__.py
skllm/models/vertex/text2text/tunable.py
skllm/prompts/builders.py
skllm/prompts/templates.py
skllm/utils/__init__.py
skllm/utils/rendering.py
skllm/utils/xml.py
scikit_llm-1.4.3.dist-info/METADATA
scikit_llm-1.4.3.dist-info/WHEEL
scikit_llm-1.4.3.dist-info/top_level.txt
scikit_llm-1.4.3.dist-info/RECORD
