Metadata-Version: 2.4
Name: scikit-llm
Version: 1.4.3
Summary: Scikit-LLM: Seamlessly integrate powerful language models like ChatGPT into scikit-learn for enhanced text analysis tasks.
Author-email: Oleh Kostromin <kostromin97@gmail.com>, Iryna Kondrashchenko <iryna230520@gmail.com>
License: MIT
Classifier: Programming Language :: Python :: 3
Classifier: License :: OSI Approved :: MIT License
Classifier: Operating System :: OS Independent
Requires-Python: >=3.9
License-File: LICENSE
Requires-Dist: scikit-learn<2.0.0,>=1.1.0
Requires-Dist: pandas<3.0.0,>=1.5.0
Requires-Dist: openai<2.0.0,>=1.2.0
Requires-Dist: tqdm<5.0.0,>=4.60.0
Requires-Dist: google-cloud-aiplatform[pipelines]<2.0.0,>=1.27.0
Provides-Extra: gguf
Requires-Dist: llama-cpp-python<0.2.83,>=0.2.82; extra == "gguf"
Provides-Extra: annoy
Requires-Dist: annoy<2.0.0,>=1.17.2; extra == "annoy"
Dynamic: license-file
